{"interfaceLanguages":{"occ":[{"children":[{"title":"Variables","type":"groupMarker"},{"path":"\/documentation\/keystonecrypto\/keystonecryptoversionnumber","title":"KeystoneCryptoVersionNumber","type":"var"},{"path":"\/documentation\/keystonecrypto\/keystonecryptoversionstring","title":"KeystoneCryptoVersionString","type":"var"}],"path":"\/documentation\/keystonecrypto","title":"KeystoneCrypto","type":"module"}],"swift":[{"children":[{"title":"Classes","type":"groupMarker"},{"children":[{"title":"Initializers","type":"groupMarker"},{"path":"\/documentation\/keystonecrypto\/keystonecrypto\/init()","title":"init()","type":"init"},{"title":"Instance Methods","type":"groupMarker"},{"path":"\/documentation\/keystonecrypto\/keystonecrypto\/decryptpinblock(pinblock:key:)","title":"func DecryptPinblock(pinblock: Pinblock, key: LocalKey) throws -> String","type":"method"},{"path":"\/documentation\/keystonecrypto\/keystonecrypto\/encryptpin(pin:key:pan:)","title":"func EncryptPin(pin: String, key: LocalKey, pan: String) throws -> Pinblock","type":"method"},{"path":"\/documentation\/keystonecrypto\/keystonecrypto\/generatelocalkey(otk:keytype:)","title":"func GenerateLocalKey(otk: OneTimeKey, keyType: LocalKey.KeyType) throws -> LocalKey","type":"method"}],"path":"\/documentation\/keystonecrypto\/keystonecrypto","title":"KeystoneCrypto","type":"class"},{"children":[{"title":"Initializers","type":"groupMarker"},{"path":"\/documentation\/keystonecrypto\/localkey\/init(wrappingkey:keytype:)","title":"init(wrappingKey: OneTimeKey, keyType: KeyType) throws","type":"init"},{"title":"Instance Methods","type":"groupMarker"},{"path":"\/documentation\/keystonecrypto\/localkey\/getencryptedkeymaterial()","title":"func getEncryptedKeyMaterial() -> String","type":"method"},{"path":"\/documentation\/keystonecrypto\/localkey\/getkcv()","title":"func getKCV() -> String","type":"method"},{"path":"\/documentation\/keystonecrypto\/localkey\/getkey()","title":"func getKey() -> [UInt8]","type":"method"},{"path":"\/documentation\/keystonecrypto\/localkey\/getkeytype()","title":"func getKeyType() -> KeyType","type":"method"},{"path":"\/documentation\/keystonecrypto\/localkey\/getwrappingkey()","title":"func getWrappingKey() -> OneTimeKey","type":"method"},{"title":"Enumerations","type":"groupMarker"},{"children":[{"title":"Enumeration Cases","type":"groupMarker"},{"path":"\/documentation\/keystonecrypto\/localkey\/keytype\/aes","title":"case AES","type":"case"},{"path":"\/documentation\/keystonecrypto\/localkey\/keytype\/tripledes","title":"case TripleDES","type":"case"},{"title":"Default Implementations","type":"groupMarker"},{"children":[{"title":"Operators","type":"groupMarker"},{"path":"\/documentation\/keystonecrypto\/localkey\/keytype\/!=(_:_:)","title":"static func != (Self, Self) -> Bool","type":"op"}],"path":"\/documentation\/keystonecrypto\/localkey\/keytype\/equatable-implementations","title":"Equatable Implementations","type":"symbol"}],"path":"\/documentation\/keystonecrypto\/localkey\/keytype","title":"LocalKey.KeyType","type":"enum"}],"path":"\/documentation\/keystonecrypto\/localkey","title":"LocalKey","type":"class"},{"children":[{"title":"Initializers","type":"groupMarker"},{"path":"\/documentation\/keystonecrypto\/onetimekey\/init(id:keymaterialbase64:)","title":"init(id: String, keyMaterialBase64: String)","type":"init"},{"title":"Instance Methods","type":"groupMarker"},{"path":"\/documentation\/keystonecrypto\/onetimekey\/getid()","title":"func getId() -> String","type":"method"}],"path":"\/documentation\/keystonecrypto\/onetimekey","title":"OneTimeKey","type":"class"},{"children":[{"title":"Initializers","type":"groupMarker"},{"path":"\/documentation\/keystonecrypto\/pinblock\/init(encryptedpinblock:pan:format:)","title":"init(encryptedPinblock: String, pan: String, format: PinblockFormat)","type":"init"},{"title":"Instance Methods","type":"groupMarker"},{"path":"\/documentation\/keystonecrypto\/pinblock\/getencryptedpinblock()","title":"func getEncryptedPinblock() -> String","type":"method"},{"path":"\/documentation\/keystonecrypto\/pinblock\/getencryptedzpk()","title":"func getEncryptedZPK() -> String?","type":"method"},{"path":"\/documentation\/keystonecrypto\/pinblock\/getformat()","title":"func getFormat() -> PinblockFormat","type":"method"},{"path":"\/documentation\/keystonecrypto\/pinblock\/getpan()","title":"func getPAN() -> String?","type":"method"},{"path":"\/documentation\/keystonecrypto\/pinblock\/getwrappingkeyid()","title":"func getWrappingKeyId() -> String?","type":"method"},{"path":"\/documentation\/keystonecrypto\/pinblock\/getzpkkcv()","title":"func getZpkKCV() -> String?","type":"method"},{"title":"Enumerations","type":"groupMarker"},{"children":[{"title":"Enumeration Cases","type":"groupMarker"},{"path":"\/documentation\/keystonecrypto\/pinblock\/pinblockformat\/aes_iso95641_4","title":"case AES_ISO95641_4","type":"case"},{"path":"\/documentation\/keystonecrypto\/pinblock\/pinblockformat\/des_iso95641_ansix98_0","title":"case DES_ISO95641_ANSIX98_0","type":"case"},{"title":"Initializers","type":"groupMarker"},{"path":"\/documentation\/keystonecrypto\/pinblock\/pinblockformat\/init(rawvalue:)","title":"init?(rawValue: String)","type":"init"},{"title":"Default Implementations","type":"groupMarker"},{"children":[{"title":"Operators","type":"groupMarker"},{"path":"\/documentation\/keystonecrypto\/pinblock\/pinblockformat\/!=(_:_:)","title":"static func != (Self, Self) -> Bool","type":"op"}],"path":"\/documentation\/keystonecrypto\/pinblock\/pinblockformat\/equatable-implementations","title":"Equatable Implementations","type":"symbol"},{"children":[{"title":"Instance Properties","type":"groupMarker"},{"path":"\/documentation\/keystonecrypto\/pinblock\/pinblockformat\/hashvalue","title":"var hashValue: Int","type":"property"},{"title":"Instance Methods","type":"groupMarker"},{"path":"\/documentation\/keystonecrypto\/pinblock\/pinblockformat\/hash(into:)","title":"func hash(into: inout Hasher)","type":"method"}],"path":"\/documentation\/keystonecrypto\/pinblock\/pinblockformat\/rawrepresentable-implementations","title":"RawRepresentable Implementations","type":"symbol"}],"path":"\/documentation\/keystonecrypto\/pinblock\/pinblockformat","title":"Pinblock.PinblockFormat","type":"enum"}],"path":"\/documentation\/keystonecrypto\/pinblock","title":"Pinblock","type":"class"},{"title":"Enumerations","type":"groupMarker"},{"children":[{"title":"Enumeration Cases","type":"groupMarker"},{"path":"\/documentation\/keystonecrypto\/keystoneexceptions\/cryptoerror(message:)","title":"case CryptoError(message: String)","type":"case"},{"path":"\/documentation\/keystonecrypto\/keystoneexceptions\/invalidinput(message:)","title":"case InvalidInput(message: String)","type":"case"},{"path":"\/documentation\/keystonecrypto\/keystoneexceptions\/invalidlocalkeyexception(message:)","title":"case InvalidLocalKeyException(message: String)","type":"case"},{"path":"\/documentation\/keystonecrypto\/keystoneexceptions\/invalidonetimekeyexception(message:)","title":"case InvalidOneTimeKeyException(message: String)","type":"case"},{"path":"\/documentation\/keystonecrypto\/keystoneexceptions\/invalidpinblockexception(message:)","title":"case InvalidPinblockException(message: String)","type":"case"},{"title":"Default Implementations","type":"groupMarker"},{"children":[{"title":"Instance Properties","type":"groupMarker"},{"path":"\/documentation\/keystonecrypto\/keystoneexceptions\/localizeddescription","title":"var localizedDescription: String","type":"property"}],"path":"\/documentation\/keystonecrypto\/keystoneexceptions\/error-implementations","title":"Error Implementations","type":"symbol"}],"path":"\/documentation\/keystonecrypto\/keystoneexceptions","title":"KeystoneExceptions","type":"enum"}],"path":"\/documentation\/keystonecrypto","title":"KeystoneCrypto","type":"module"}]},"schemaVersion":{"major":0,"minor":1,"patch":1}}